Workbook

Sheet Sheet1
A3: Row Labels | B3: Count of Column14
A4: Agra | B4: 15
A5: Bhopal | B5: 8
A6: City | B6: 1
A7: Delhi | B7: 12
A8: Jaipur | B8: 10
A9: Kanpur | B9: 7
A10: Lucknow | B10: 10
A11: Noida | B11: 12
A12: Patna | B12: 11 | L12: Row Labels | M12: Count of Column13
A13: Prayagraj | B13: 9 | L13: Aman | M13: 18
A14: Varanasi | B14: 6 | L14: Bhavna | M14: 13
A15: Grand Total | B15: 101 | L15: Chetan | M15: 20
L16: Deepak | M16: 27
L17: Esha | M17: 22
L18: Salesperson | M18: 1
L19: Grand Total | M19: 101
M26: STATE | N26: SALES
M27: Uttar Pradesh | N27: =SUMIF(Sales_Data!E:E,M27,Sales_Data!M:M) -> 1280588
M28: Delhi | N28: =SUMIF(Sales_Data!E:E,M28,Sales_Data!M:M) -> 134788.5
M29: Rajasthan | N29: =SUMIF(Sales_Data!E:E,M29,Sales_Data!M:M) -> 354412
M30: Bihar | N30: =SUMIF(Sales_Data!E:E,M30,Sales_Data!M:M) -> 901482.5
M31: Madhya Pradesh | N31: =SUMIF(Sales_Data!E:E,M31,Sales_Data!M:M) -> 92874

Sheet Sheet5
O2: Row Labels | P2: Count of Column16
A3: Row Labels | B3: Count of Column2 | O3: Backpack | P3: 4
A4: Accessories | B4: 27 | O4: Calculator | P4: 5
A5: Category | B5: 1 | O5: Desk | P5: 4
A6: Electronics | B6: 49 | O6: External HDD | P6: 3
A7: Furniture | B7: 10 | O7: Headphones | P7: 3
A8: Stationery | B8: 14 | O8: Keyboard | P8: 4
A9: Grand Total | B9: 101 | O9: Laptop | P9: 9
O10: Monitor | P10: 6
O11: Mouse | P11: 5
O12: Notebook | P12: 5
O13: Office Chair | P13: 6
O14: Pen Set | P14: 4
O15: Power Bank | P15: 8
O16: Printer | P16: 3
O17: Product | P17: 1
O18: Smartphone | P18: 3
O19: Smartwatch | P19: 8
O20: Speaker | P20: 5
O21: Tablet | P21: 4
... O24: Grand Total | P24: 101

Sheet Sales_Data
A1: Column1 | B1: Column2 | C1: Column3 | D1: Column4 | E1: Column5 | F1: Column6 | G1: Column7 | H1: Column8 | I1: Column9 | J1: Column10 | K1: Column11 | L1: Column12 | M1: Column13 | N1: Column14 | O1: Column15 | P1: Column16 | Q1: Column17 | R1: Column18 | S1: Column19
A2: Order_ID | B2: Order_Date | C2: Customer_Name | D2: City | E2: State | F2: Product | G2: Category | H2: Quantity | I2: Unit_Price | J2: Discount_% | K2: Gross_Sales | L2: Discount_Amount | M2: Net_Sales | N2: Sales_Channel | O2: Payment_Method | P2: Order_Status | Q2: Salesperson | R2: SALE PERFOMANCE | S2: Sales Classification
A3: ORD0100 | B3: 46265 | C3: Nisha Yadav | D3: Jaipur | E3: Uttar Pradesh | F3: USB Drive | G3: Accessories | H3: 4 | I3: 8100 | J3: 0 | K3: 2960 | L3: 0 | M3: 148741.5 | N3: Website | O3: Credit Card | P3: Delivered | Q3: Esha | R3: =IF(M2>5000,"HIGH","LOW") -> HIGH | S3: =IF(M2>=50000,"High",IF(M2>=25000,"Medium","Low")) -> High
A4: ORD0099 | B4: 46029 | C4: Kavya Mishra | D4: Delhi | E4: Uttar Pradesh | F4: Office Chair | G4: Furniture | H4: 1 | I4: 8100 | J4: 0.15 | K4: 8800 | L4: 1320 | M4: 27264 | N4: Marketplace | O4: Credit Card | P4: Delivered | Q4: Aman | R4: =IF(M3>5000,"HIGH","LOW") -> HIGH | S4: =IF(M3>=50000,"High",IF(M3>=25000,"Medium","Low")) -> High
A5: ORD0098 | B5: 46026 | C5: Priya Kumar | D5: Kanpur | E5: Uttar Pradesh | F5: Desk | G5: Furniture | H5: 5 | I5: 8100 | J5: 0.15 | K5: 31650 | L5: 4747.5 | M5: 102924 | N5: Mobile App | O5: Debit Card | P5: Delivered | Q5: Esha | R5: =IF(M4>5000,"HIGH","LOW") -> HIGH | S5: =IF(M4>=50000,"High",IF(M4>=25000,"Medium","Low")) -> Medium
A6: ORD0097 | B6: 46229 | C6: Amit Yadav | D6: Patna | E6: Uttar Pradesh | F6: Printer | G6: Electronics | H6: 2 | I6: 8100 | J6: 0.15 | K6: 18080 | L6: 2712 | M6: 40500 | N6: Mobile App | O6: UPI | P6: Delivered | Q6: Bhavna | R6: =IF(M5>5000,"HIGH","LOW") -> HIGH | S6: =IF(M5>=50000,"High",IF(M5>=25000,"Medium","Low")) -> High
A7: ORD0096 | B7: 46214 | C7: Riya Singh | D7: Noida | E7: Madhya Pradesh | F7: Smartwatch | G7: Electronics | H7: 1 | I7: 8100 | J7: 0.1 | K7: 4870 | L7: 487 | M7: 39900 | N7: Marketplace | O7: Debit Card | P7: Delivered | Q7: Esha | R7: =IF(M6>5000,"HIGH","LOW") -> HIGH | S7: =IF(M6>=50000,"High",IF(M6>=25000,"Medium","Low")) -> Medium
A8: ORD0095 | B8: 46183 | C8: Aditya Gupta | D8: Kanpur | E8: Uttar Pradesh | F8: Speaker | G8: Electronics | H8: 3 | I8: 8100 | J8: 0.05 | K8: 9330 | L8: 466.5 | M8: 621 | N8: Mobile App | O8: UPI | P8: Delivered | Q8: Esha | R8: =IF(M7>5000,"HIGH","LOW") -> HIGH | S8: =IF(M7>=50000,"High",IF(M7>=25000,"Medium","Low")) -> Medium
A9: ORD0094 | B9: 46236 | C9: Pooja Verma | D9: Prayagraj | E9: Uttar Pradesh | F9: External HDD | G9: Electronics | H9: 1 | I9: 8100 | J9: 0.15 | K9: 7030 | L9: 1054.5 | M9: 3744 | N9: Marketplace | O9: Debit Card | P9: Cancelled | Q9: Bhavna | R9: =IF(M8>5000,"HIGH","LOW") -> LOW | S9: =IF(M8>=50000,"High",IF(M8>=25000,"Medium","Low")) -> Low
A10: ORD0093 | B10: 46114 | C10: Pooja Sharma | D10: Delhi | E10: Uttar Pradesh | F10: Calculator | G10: Stationery | H10: 1 | I10: 8100 | J10: 0.2 | K10: 520 | L10: 104 | M10: 31184 | N10: Marketplace | O10: Net Banking | P10: Delivered | Q10: Chetan | R10: =IF(M9>5000,"HIGH","LOW") -> LOW | S10: =IF(M9>=50000,"High",IF(M9>=25000,"Medium","Low")) -> Low
A11: ORD0092 | B11: 46173 | C11: Simran Gupta | D11: Agra | E11: Uttar Pradesh | F11: Power Bank | G11: Accessories | H11: 2 | I11: 8100 | J11: 0.1 | K11: 2920 | L11: 292 | M11: 7552 | N11: Mobile App | O11: Debit Card | P11: Delivered | Q11: Bhavna | R11: =IF(M10>5000,"HIGH","LOW") -> HIGH | S11: =IF(M10>=50000,"High",IF(M10>=25000,"Medium","Low")) -> Medium
A12: ORD0091 | B12: 46059 | C12: Vikas Kumar | D12: Delhi | E12: Uttar Pradesh | F12: Speaker | G12: Electronics | H12: 2 | I12: 8100 | J12: 0.2 | K12: 6000 | L12: 1200 | M12: 11760 | N12: Mobile App | O12: UPI | P12: Delivered | Q12: Deepak | R12: =IF(M11>5000,"HIGH","LOW") -> HIGH | S12: =IF(M11>=50000,"High",IF(M11>=25000,"Medium","Low")) -> Low
A13: ORD0090 | B13: 46158 | C13: Neha Singh | D13: Agra | E13: Delhi | F13: Office Chair | G13: Furniture | H13: 3 | I13: 8100 | J13: 0.05 | K13: 25140 | L13: 1257 | M13: 9664 | N13: Website | O13: UPI | P13: Delivered | Q13: Esha | R13: =IF(M12>5000,"HIGH","LOW") -> HIGH | S13: =IF(M12>=50000,"High",IF(M12>=25000,"Medium","Low")) -> Low
A14: ORD0089 | B14: 46136 | C14: Pooja Sharma | D14: Lucknow | E14: Uttar Pradesh | F14: Notebook | G14: Stationery | H14: 1 | I14: 8100 | J14: 0 | K14: 190 | L14: 0 | M14: 324 | N14: Website | O14: Debit Card | P14: Delivered | Q14: Aman | R14: =IF(M13>5000,"HIGH","LOW") -> HIGH | S14: =IF(M13>=50000,"High",IF(M13>=25000,"Medium","Low")) -> Low
... A102: ORD0001 | B102: 46211 | C102: Kavya Yadav | D102: Lucknow | E102: Rajasthan | F102: Laptop | G102: Electronics | H102: 3 | I102: 8100 | J102: 0.05 | K102: 156570 | L102: 7828.5 | M102: 2960 | N102: Marketplace | O102: Net Banking | P102: Delivered | Q102: Aman | R102: =IF(M101>5000,"HIGH","LOW") -> HIGH | S102: =IF(M101>=50000,"High",IF(M101>=25000,"Medium","Low")) -> Low
G104: =COUNTIFS(Sales_Data!E2:E102,"Delhi",Sales_Data!G2:G102,"Electronics") -> 8 | H104: =SUM([1]Sales_Data!H2:H101) -> 276 | K104: =SUM([1]Sales_Data!K2:K101) -> 2955590 | M104: =AVERAGE([2]Sales_Data!M3:M102) -> 26418.217 | N104: =COUNTIF(N2:N102,"WEBSITE") -> 34 | P104: =COUNTIFS(Sales_Data!P2:P102,"Delivered") -> 87
M105: =MAX(Sales_Data!M3:M103) -> 299650
G106: =COUNTIFS(Sales_Data!G2:G101,"ELECTRONICS",Sales_Data!D2:D101,"Delhi") -> 5 | P106: =COUNTIFS(Sales_Data!P2:P102,"Delivered",Sales_Data!N2:N102,"Website") -> 31
M107: =(MIN(Sales_Data!M2:M102)) -> 180 | P107: =(COUNTIFS(Sales_Data!P2:P102,"Shipped",Sales_Data!N2:N102,"MOBILE App")) -> 2
M110: =C2&"_"&D2 -> Customer_Name_City
M111: =C3&":"&D3 -> Nisha Yadav:Jaipur
